cratedb_django/__init__.py
cratedb_django/base.py
cratedb_django/client.py
cratedb_django/compiler.py
cratedb_django/creation.py
cratedb_django/features.py
cratedb_django/introspection.py
cratedb_django/operations.py
cratedb_django/schema.py
cratedb_django/fields/__init__.py
cratedb_django/fields/array.py
cratedb_django/fields/base.py
cratedb_django/fields/json.py
cratedb_django/models/__init__.py
cratedb_django/models/functions.py
cratedb_django/models/model.py
cratedb_django-0.0.8.dist-info/licenses/LICENSE.md
cratedb_django-0.0.8.dist-info/METADATA
cratedb_django-0.0.8.dist-info/WHEEL
cratedb_django-0.0.8.dist-info/top_level.txt
cratedb_django-0.0.8.dist-info/RECORD
