Metadata-Version: 2.4
Name: cratedb-django
Version: 0.0.8
Summary: CrateDB connector for Django 
Author-email: Ivan <surister98@gmail.com>
License: Copyright 2025 github.com/surister
Project-URL: Home Page, https://github.com/surister/cratedb-django
Project-URL: Documentation, https://github.com/surister/cratedb-django
Project-URL: Repository, https://github.com/surister/cratedb-django.git
Project-URL: GitHub, https://github.com/surister/cratedb-django
Project-URL: Changelog, https://github.com/surister/cratedb-django/releases
Classifier: Development Status :: 3 - Alpha
Classifier: Framework :: Django
Classifier: Topic :: Database
Classifier: Topic :: Database :: Front-Ends
Classifier: Natural Language :: English
Classifier: Intended Audience :: Developers
Classifier: License :: OSI Approved :: MIT License
Classifier: Operating System :: OS Independent
Classifier: Programming Language :: Python
Classifier: Programming Language :: Python :: 3
Classifier: Programming Language :: Python :: 3 :: Only
Requires-Python: >=3.10
License-File: LICENSE.md
Requires-Dist: crate==2.0.0
Requires-Dist: django>=5.2
Dynamic: license-file
